enrich_omics/EnrichR.py
enrich_omics/OpenTargets.py
enrich_omics/__init__.py
enrich_omics-0.2.1.dist-info/LICENSE
enrich_omics-0.2.1.dist-info/METADATA
enrich_omics-0.2.1.dist-info/WHEEL
enrich_omics-0.2.1.dist-info/top_level.txt
enrich_omics-0.2.1.dist-info/RECORD
