Metadata-Version: 2.1
Name: enrich-omics
Version: 0.2.1
Summary: Package to perform enrichment analysis in python using EnrichR and OpenTargets APIs
Home-page: UNKNOWN
Author: Sara Masarone
License: UNKNOWN
Platform: UNKNOWN
Classifier: Programming Language :: Python :: 3
Classifier: License :: OSI Approved :: MIT License
Classifier: Operating System :: OS Independent
Requires-Python: >=3.6
Requires-Dist: numpy (>=1.22.1)
Requires-Dist: pandas (>=1.0.5)
Requires-Dist: altair (>=4.1.0)
Requires-Dist: requests (>=2.24.0)
Requires-Dist: mygene (>=3.2.2)
